motivate_me/__init__.py
motivate_me-0.1.0.dist-info/LICENSE
motivate_me-0.1.0.dist-info/METADATA
motivate_me-0.1.0.dist-info/WHEEL
motivate_me-0.1.0.dist-info/top_level.txt
motivate_me-0.1.0.dist-info/RECORD
