Metadata-Version: 2.1
Name: motivate-me
Version: 0.1.0
Summary: A package leveraging ChatGPT to print out motivational quotes and one-liners.
Home-page: https://github.com/wxbdm/motivate-me
Author: Brandon Molyneaux
Author-email: brandon@learningcodeonline.com
Classifier: Programming Language :: Python :: 3
Classifier: License :: OSI Approved :: MIT License
Classifier: Operating System :: OS Independent
Requires-Python: >=3.6
License-File: LICENSE
Requires-Dist: openai (==0.27.0)
